{
  "version": "1.0",
  "lastUpdated": "2026-03-05T16:54:56.515Z",
  "hospitalYield": [
    {
      "date": "2026-02-03",
      "revenue": 28228,
      "patients": 20,
      "consultations": 14
    },
    {
      "date": "2026-02-04",
      "revenue": 25966,
      "patients": 22,
      "consultations": 19
    },
    {
      "date": "2026-02-05",
      "revenue": 35646,
      "patients": 25,
      "consultations": 12
    },
    {
      "date": "2026-02-06",
      "revenue": 24019,
      "patients": 27,
      "consultations": 11
    },
    {
      "date": "2026-02-07",
      "revenue": 17702,
      "patients": 35,
      "consultations": 10
    },
    {
      "date": "2026-02-08",
      "revenue": 24089,
      "patients": 29,
      "consultations": 18
    },
    {
      "date": "2026-02-09",
      "revenue": 32722,
      "patients": 13,
      "consultations": 15
    },
    {
      "date": "2026-02-10",
      "revenue": 47852,
      "patients": 9,
      "consultations": 23
    },
    {
      "date": "2026-02-11",
      "revenue": 35096,
      "patients": 16,
      "consultations": 13
    },
    {
      "date": "2026-02-12",
      "revenue": 26126,
      "patients": 7,
      "consultations": 10
    },
    {
      "date": "2026-02-13",
      "revenue": 31038,
      "patients": 22,
      "consultations": 6
    },
    {
      "date": "2026-02-14",
      "revenue": 15528,
      "patients": 22,
      "consultations": 23
    },
    {
      "date": "2026-02-15",
      "revenue": 48202,
      "patients": 16,
      "consultations": 4
    },
    {
      "date": "2026-02-16",
      "revenue": 49677,
      "patients": 9,
      "consultations": 10
    },
    {
      "date": "2026-02-17",
      "revenue": 48734,
      "patients": 10,
      "consultations": 3
    },
    {
      "date": "2026-02-18",
      "revenue": 47343,
      "patients": 22,
      "consultations": 16
    },
    {
      "date": "2026-02-19",
      "revenue": 24274,
      "patients": 13,
      "consultations": 17
    },
    {
      "date": "2026-02-20",
      "revenue": 48810,
      "patients": 39,
      "consultations": 7
    },
    {
      "date": "2026-02-21",
      "revenue": 41438,
      "patients": 13,
      "consultations": 14
    },
    {
      "date": "2026-02-22",
      "revenue": 18055,
      "patients": 16,
      "consultations": 10
    },
    {
      "date": "2026-02-23",
      "revenue": 43080,
      "patients": 31,
      "consultations": 2
    },
    {
      "date": "2026-02-24",
      "revenue": 33422,
      "patients": 6,
      "consultations": 3
    },
    {
      "date": "2026-02-25",
      "revenue": 47455,
      "patients": 18,
      "consultations": 18
    },
    {
      "date": "2026-02-26",
      "revenue": 37889,
      "patients": 8,
      "consultations": 0
    },
    {
      "date": "2026-02-27",
      "revenue": 17874,
      "patients": 28,
      "consultations": 8
    },
    {
      "date": "2026-02-28",
      "revenue": 17539,
      "patients": 15,
      "consultations": 9
    },
    {
      "date": "2026-03-01",
      "revenue": 35157,
      "patients": 16,
      "consultations": 12
    },
    {
      "date": "2026-03-02",
      "revenue": 31486,
      "patients": 23,
      "consultations": 3
    },
    {
      "date": "2026-03-03",
      "revenue": 21907,
      "patients": 20,
      "consultations": 19
    },
    {
      "date": "2026-03-04",
      "revenue": 28827,
      "patients": 25,
      "consultations": 15
    },
    {
      "date": "2026-03-05",
      "revenue": 25013,
      "patients": 28,
      "consultations": 14
    }
  ]
}
